MANIFEST.in
README.rst
setup.py
django_crispy_forms_fancy_formsets.egg-info/PKG-INFO
django_crispy_forms_fancy_formsets.egg-info/SOURCES.txt
django_crispy_forms_fancy_formsets.egg-info/dependency_links.txt
django_crispy_forms_fancy_formsets.egg-info/not-zip-safe
django_crispy_forms_fancy_formsets.egg-info/top_level.txt
fancy_formsets/__init__.py
fancy_formsets/forms.py
fancy_formsets/helper.py
fancy_formsets/views.py
fancy_formsets/widgets.py
fancy_formsets/locale/da/LC_MESSAGES/django.mo
fancy_formsets/locale/da/LC_MESSAGES/django.po
fancy_formsets/static/fancy_formsets/fancy_formsets.css
fancy_formsets/static/fancy_formsets/fancy_formsets.js
fancy_formsets/templates/fancy_formsets_bootstrap/field.html
fancy_formsets/templates/fancy_formsets_bootstrap/field_readonly.html
fancy_formsets/templates/fancy_formsets_bootstrap/form.html
fancy_formsets/templates/fancy_formsets_bootstrap/formset.html
fancy_formsets/templates/fancy_formsets_bootstrap/formsets.html
fancy_formsets/templates/fancy_formsets_bootstrap/tfoot.html
fancy_formsets/templates/fancy_formsets_bootstrap/th.html
fancy_formsets/templatetags/__init__.py
fancy_formsets/templatetags/fancy_formsets_tags.py
test_project/__init__.py
test_project/manage.py
test_project/settings.py
test_project/urls.py
test_project/fancy_formsets/__init__.py
test_project/fancy_formsets/forms.py
test_project/fancy_formsets/helper.py
test_project/fancy_formsets/views.py
test_project/fancy_formsets/widgets.py
test_project/fancy_formsets/templatetags/__init__.py
test_project/fancy_formsets/templatetags/fancy_formsets_tags.py
test_project/test_app/__init__.py
test_project/test_app/admin.py
test_project/test_app/formsets.py
test_project/test_app/models.py
test_project/test_app/tests.py
test_project/test_app/views.py